eox_audit_model/__init__.py
eox_audit_model/admin.py
eox_audit_model/apps.py
eox_audit_model/constants.py
eox_audit_model/context_managers.py
eox_audit_model/decorators.py
eox_audit_model/exceptions.py
eox_audit_model/models.py
eox_audit_model/tasks.py
eox_audit_model/migrations/0001_initial.py
eox_audit_model/migrations/0002_auditnote.py
eox_audit_model/migrations/0003_auto_20201224_0031.py
eox_audit_model/migrations/__init__.py
eox_audit_model/settings/__init__.py
eox_audit_model/settings/common.py
eox_audit_model/settings/production.py
eox_audit_model/settings/test.py
eox_audit_model/tests/__init__.py
eox_audit_model/tests/tests_decorators.py
eox_audit_model/tests/tests_models.py
eox_audit_model/tests/tests_tasks.py
eox_audit_model-6.1.0.dist-info/licenses/AUTHORS.txt
eox_audit_model-6.1.0.dist-info/licenses/LICENSE.txt
eox_audit_model-6.1.0.dist-info/METADATA
eox_audit_model-6.1.0.dist-info/WHEEL
eox_audit_model-6.1.0.dist-info/entry_points.txt
eox_audit_model-6.1.0.dist-info/top_level.txt
eox_audit_model-6.1.0.dist-info/RECORD
