Metadata-Version: 2.4
Name: eox_audit_model
Version: 6.1.0
Summary: Django eduNEXT Audit Model
Author: eduNEXT
Author-email: contact@edunext.co
License: AGPL
Classifier: Development Status :: 5 - Production/Stable
Classifier: Framework :: Django :: 4.2
Classifier: Framework :: Django :: 5.2
Classifier: Intended Audience :: Developers
Classifier: License :: OSI Approved :: GNU Affero General Public License v3
Classifier: Operating System :: OS Independent
Classifier: Programming Language :: Python :: 3.11
Classifier: Programming Language :: Python :: 3.12
License-File: LICENSE.txt
License-File: AUTHORS.txt
Requires-Dist: jsonfield
Requires-Dist: django-crum
Requires-Dist: Django
Requires-Dist: celery
Requires-Dist: django-ipware
Dynamic: author
Dynamic: author-email
Dynamic: classifier
Dynamic: description
Dynamic: description-content-type
Dynamic: license
Dynamic: license-file
Dynamic: requires-dist
Dynamic: summary
